inkwell/__init__.py
inkwell/api/__init__.py
inkwell/api/document.py
inkwell/api/figure.py
inkwell/api/file.py
inkwell/api/page.py
inkwell/api/table.py
inkwell/api/text.py
inkwell/components/__init__.py
inkwell/components/base.py
inkwell/components/document.py
inkwell/components/elements.py
inkwell/components/layout.py
inkwell/components/utils.py
inkwell/figure_extractor/__init__.py
inkwell/figure_extractor/base.py
inkwell/figure_extractor/config.py
inkwell/figure_extractor/figure_extractor.py
inkwell/figure_extractor/figure_extractor_factory.py
inkwell/figure_extractor/minicpm_figure_extractor.py
inkwell/figure_extractor/openai_4o_mini_figure_extractor.py
inkwell/figure_extractor/phi3v_figure_extractor.py
inkwell/figure_extractor/prompts.py
inkwell/io/__init__.py
inkwell/io/input.py
inkwell/layout_detector/__init__.py
inkwell/layout_detector/base.py
inkwell/layout_detector/config/Base-RCNN-FPN.yml
inkwell/layout_detector/config/__init__.py
inkwell/layout_detector/config/cascade_layoutlmv3.yml
inkwell/layout_detector/config/faster_rcnn_detectron2_cfg.yml
inkwell/layout_detector/config/layout_detector_configurations.yml
inkwell/layout_detector/detectron2_engine.py
inkwell/layout_detector/faster_rcnn_detector.py
inkwell/layout_detector/layout_detector.py
inkwell/layout_detector/layout_factory.py
inkwell/layout_detector/layoutlmv3/__init__.py
inkwell/layout_detector/layoutlmv3/backbone.py
inkwell/layout_detector/layoutlmv3/beit.py
inkwell/layout_detector/layoutlmv3/deit.py
inkwell/layout_detector/layoutlmv3/layoutlmft/__init__.py
inkwell/layout_detector/layoutlmv3/layoutlmft/models/__init__.py
inkwell/layout_detector/layoutlmv3/layoutlmft/models/layoutlmv3/__init__.py
inkwell/layout_detector/layoutlmv3/layoutlmft/models/layoutlmv3/configuration_layoutlmv3.py
inkwell/layout_detector/layoutlmv3/layoutlmft/models/layoutlmv3/modeling_layoutlmv3.py
inkwell/layout_detector/layoutlmv3/layoutlmft/models/layoutlmv3/tokenization_layoutlmv3.py
py_inkwell-0.0.39.dist-info/LICENSE
py_inkwell-0.0.39.dist-info/METADATA
py_inkwell-0.0.39.dist-info/WHEEL
py_inkwell-0.0.39.dist-info/RECORD
