Metadata-Version: 2.1
Name: py-inkwell
Version: 0.0.39
Summary: Python library for document processing
Home-page: https://github.com/tensorlakeai/indexify
License: Apache 2.0
Author: Mohit Raghavendra
Author-email: mohithmitra@gmail.com
Requires-Python: >=3.9,<4.0
Classifier: License :: Other/Proprietary License
Classifier: Programming Language :: Python :: 3
Classifier: Programming Language :: Python :: 3.9
Classifier: Programming Language :: Python :: 3.10
Classifier: Programming Language :: Python :: 3.11
Classifier: Programming Language :: Python :: 3.12
Classifier: Programming Language :: Python :: 3.13
Provides-Extra: api
Provides-Extra: inference
Requires-Dist: Pillow (>=9.5.0,<10.0.0) ; extra == "inference"
Requires-Dist: accelerate (>=0.34.2,<0.35.0) ; extra == "inference"
Requires-Dist: albumentations (>=1.4.16,<2.0.0) ; extra == "inference"
Requires-Dist: iopath (>=0.1.9,<0.2.0) ; extra == "inference"
Requires-Dist: numpy (<2.0.0) ; extra == "inference"
Requires-Dist: openai (>=1.46.1,<2.0.0) ; extra == "inference"
Requires-Dist: opencv-python (>=4.10.0.84,<5.0.0.0) ; extra == "inference"
Requires-Dist: pandas (>=2.2.2,<3.0.0) ; extra == "inference"
Requires-Dist: pdfplumber (>=0.11.4,<0.12.0) ; extra == "inference"
Requires-Dist: pydantic (>=2.8,<3.0)
Requires-Dist: pytesseract (>=0.3.13,<0.4.0) ; extra == "inference"
Requires-Dist: pyyaml (>=6.0.2,<7.0.0)
Requires-Dist: timm (>=1.0.9,<2.0.0) ; extra == "inference"
Requires-Dist: torch (>=2.3.1,<3.0.0) ; extra == "inference"
Requires-Dist: torchvision (>=0.19,<0.20) ; extra == "inference"
Requires-Dist: tqdm (>=4.66.5,<5.0.0)
Requires-Dist: transformers (>=4.44.2,<5.0.0) ; extra == "inference"
Project-URL: Repository, https://github.com/tensorlakeai/inkwell
